circuit_breaker_labs/__init__.py
circuit_breaker_labs/api/__init__.py
circuit_breaker_labs/api/api_keys/__init__.py
circuit_breaker_labs/api/api_keys/monthly_quota_get.py
circuit_breaker_labs/api/api_keys/validate_api_key_get.py
circuit_breaker_labs/api/evaluations/__init__.py
circuit_breaker_labs/api/evaluations/multi_turn_evaluate_system_prompt_post.py
circuit_breaker_labs/api/evaluations/multiturn_evaluate_openai_fine_tune_post.py
circuit_breaker_labs/api/evaluations/single_turn_evaluate_openai_fine_tune_post.py
circuit_breaker_labs/api/evaluations/singleturn_evaluate_system_prompt_post.py
circuit_breaker_labs/api/health_checks/__init__.py
circuit_breaker_labs/api/health_checks/ping_get.py
circuit_breaker_labs/api/health_checks/version_get.py
circuit_breaker_labs/client.py
circuit_breaker_labs/errors.py
circuit_breaker_labs/models/__init__.py
circuit_breaker_labs/models/http_validation_error.py
circuit_breaker_labs/models/internal_server_error.py
circuit_breaker_labs/models/internal_server_error_response.py
circuit_breaker_labs/models/message.py
circuit_breaker_labs/models/monthly_quota_response.py
circuit_breaker_labs/models/multi_turn_evaluate_open_ai_finetune_request.py
circuit_breaker_labs/models/multi_turn_evaluate_system_prompt_request.py
circuit_breaker_labs/models/multi_turn_failed_test_result.py
circuit_breaker_labs/models/multi_turn_run_tests_response.py
circuit_breaker_labs/models/multi_turn_test_type.py
circuit_breaker_labs/models/not_found_error.py
circuit_breaker_labs/models/not_found_response.py
circuit_breaker_labs/models/ping_response.py
circuit_breaker_labs/models/quota_exceeded_error.py
circuit_breaker_labs/models/quota_exceeded_response.py
circuit_breaker_labs/models/role.py
circuit_breaker_labs/models/single_turn_evaluate_open_ai_finetune_request.py
circuit_breaker_labs/models/single_turn_evaluate_system_prompt_request.py
circuit_breaker_labs/models/single_turn_failed_test_result.py
circuit_breaker_labs-1.0.6.dist-info/WHEEL
circuit_breaker_labs-1.0.6.dist-info/METADATA
circuit_breaker_labs-1.0.6.dist-info/RECORD
