Metadata-Version: 2.3
Name: circuit-breaker-labs
Version: 1.0.6
Summary: A client library for accessing Circuit Breaker Labs API
Requires-Dist: httpx>=0.23.0,<0.29.0
Requires-Dist: attrs>=22.2.0
Requires-Dist: python-dateutil>=2.8.0,<3
Requires-Dist: types-python-dateutil>=2.9.0.20251115
Requires-Python: >=3.10
